{
  "name": "flowery:pot/acacia",
  "fallback": "minecraft:empty",
  "elements": [
    {
      "weight": 1,
      "element": {
        "element_type": "minecraft:single_pool_element",
        "location": "flowery:pot/acacia/0",
        "projection": "rigid",
        "processors": "minecraft:empty"
      }
    },
    {
      "weight": 1,
      "element": {
        "element_type": "minecraft:single_pool_element",
        "location": "flowery:pot/acacia/1",
        "projection": "rigid",
        "processors": "minecraft:empty"
      }
    },
    {
      "weight": 1,
      "element": {
        "element_type": "minecraft:single_pool_element",
        "location": "flowery:pot/acacia/10",
        "projection": "rigid",
        "processors": "minecraft:empty"
      }
    },
    {
      "weight": 1,
      "element": {
        "element_type": "minecraft:single_pool_element",
        "location": "flowery:pot/acacia/11",
        "projection": "rigid",
        "processors": "minecraft:empty"
      }
    },
    {
      "weight": 1,
      "element": {
        "element_type": "minecraft:single_pool_element",
        "location": "flowery:pot/acacia/12",
        "projection": "rigid",
        "processors": "minecraft:empty"
      }
    },
    {
      "weight": 1,
      "element": {
        "element_type": "minecraft:single_pool_element",
        "location": "flowery:pot/acacia/13",
        "projection": "rigid",
        "processors": "minecraft:empty"
      }
    },
    {
      "weight": 1,
      "element": {
        "element_type": "minecraft:single_pool_element",
        "location": "flowery:pot/acacia/14",
        "projection": "rigid",
        "processors": "minecraft:empty"
      }
    },
    {
      "weight": 1,
      "element": {
        "element_type": "minecraft:single_pool_element",
        "location": "flowery:pot/acacia/15",
        "projection": "rigid",
        "processors": "minecraft:empty"
      }
    },
    {
      "weight": 1,
      "element": {
        "element_type": "minecraft:single_pool_element",
        "location": "flowery:pot/acacia/16",
        "projection": "rigid",
        "processors": "minecraft:empty"
      }
    },
    {
      "weight": 1,
      "element": {
        "element_type": "minecraft:single_pool_element",
        "location": "flowery:pot/acacia/17",
        "projection": "rigid",
        "processors": "minecraft:empty"
      }
    },
    {
      "weight": 1,
      "element": {
        "element_type": "minecraft:single_pool_element",
        "location": "flowery:pot/acacia/18",
        "projection": "rigid",
        "processors": "minecraft:empty"
      }
    },
    {
      "weight": 1,
      "element": {
        "element_type": "minecraft:single_pool_element",
        "location": "flowery:pot/acacia/19",
        "projection": "rigid",
        "processors": "minecraft:empty"
      }
    },
    {
      "weight": 1,
      "element": {
        "element_type": "minecraft:single_pool_element",
        "location": "flowery:pot/acacia/2",
        "projection": "rigid",
        "processors": "minecraft:empty"
      }
    },
    {
      "weight": 1,
      "element": {
        "element_type": "minecraft:single_pool_element",
        "location": "flowery:pot/acacia/20",
        "projection": "rigid",
        "processors": "minecraft:empty"
      }
    },
    {
      "weight": 1,
      "element": {
        "element_type": "minecraft:single_pool_element",
        "location": "flowery:pot/acacia/21",
        "projection": "rigid",
        "processors": "minecraft:empty"
      }
    },
    {
      "weight": 1,
      "element": {
        "element_type": "minecraft:single_pool_element",
        "location": "flowery:pot/acacia/22",
        "projection": "rigid",
        "processors": "minecraft:empty"
      }
    },
    {
      "weight": 1,
      "element": {
        "element_type": "minecraft:single_pool_element",
        "location": "flowery:pot/acacia/23",
        "projection": "rigid",
        "processors": "minecraft:empty"
      }
    },
    {
      "weight": 1,
      "element": {
        "element_type": "minecraft:single_pool_element",
        "location": "flowery:pot/acacia/24",
        "projection": "rigid",
        "processors": "minecraft:empty"
      }
    },
    {
      "weight": 1,
      "element": {
        "element_type": "minecraft:single_pool_element",
        "location": "flowery:pot/acacia/25",
        "projection": "rigid",
        "processors": "minecraft:empty"
      }
    },
    {
      "weight": 1,
      "element": {
        "element_type": "minecraft:single_pool_element",
        "location": "flowery:pot/acacia/26",
        "projection": "rigid",
        "processors": "minecraft:empty"
      }
    },
    {
      "weight": 1,
      "element": {
        "element_type": "minecraft:single_pool_element",
        "location": "flowery:pot/acacia/27",
        "projection": "rigid",
        "processors": "minecraft:empty"
      }
    },
    {
      "weight": 1,
      "element": {
        "element_type": "minecraft:single_pool_element",
        "location": "flowery:pot/acacia/28",
        "projection": "rigid",
        "processors": "minecraft:empty"
      }
    },
    {
      "weight": 1,
      "element": {
        "element_type": "minecraft:single_pool_element",
        "location": "flowery:pot/acacia/29",
        "projection": "rigid",
        "processors": "minecraft:empty"
      }
    },
    {
      "weight": 1,
      "element": {
        "element_type": "minecraft:single_pool_element",
        "location": "flowery:pot/acacia/3",
        "projection": "rigid",
        "processors": "minecraft:empty"
      }
    },
    {
      "weight": 1,
      "element": {
        "element_type": "minecraft:single_pool_element",
        "location": "flowery:pot/acacia/4",
        "projection": "rigid",
        "processors": "minecraft:empty"
      }
    },
    {
      "weight": 1,
      "element": {
        "element_type": "minecraft:single_pool_element",
        "location": "flowery:pot/acacia/5",
        "projection": "rigid",
        "processors": "minecraft:empty"
      }
    },
    {
      "weight": 1,
      "element": {
        "element_type": "minecraft:single_pool_element",
        "location": "flowery:pot/acacia/6",
        "projection": "rigid",
        "processors": "minecraft:empty"
      }
    },
    {
      "weight": 1,
      "element": {
        "element_type": "minecraft:single_pool_element",
        "location": "flowery:pot/acacia/7",
        "projection": "rigid",
        "processors": "minecraft:empty"
      }
    },
    {
      "weight": 1,
      "element": {
        "element_type": "minecraft:single_pool_element",
        "location": "flowery:pot/acacia/8",
        "projection": "rigid",
        "processors": "minecraft:empty"
      }
    },
    {
      "weight": 1,
      "element": {
        "element_type": "minecraft:single_pool_element",
        "location": "flowery:pot/acacia/9",
        "projection": "rigid",
        "processors": "minecraft:empty"
      }
    }
  ]
}